jsonrpcx/__init__.py
jsonrpcx-4.1.0.dist-info/LICENCE
jsonrpcx-4.1.0.dist-info/METADATA
jsonrpcx-4.1.0.dist-info/WHEEL
jsonrpcx-4.1.0.dist-info/top_level.txt
jsonrpcx-4.1.0.dist-info/RECORD
