Metadata-Version: 2.1
Name: jsonrpcx
Version: 4.1.0
Summary: A battle tested Python JSON-RPC2.0 library supporting client and server code in sync and async fashion.
Home-page: https://codeberg.org/_laphilipa/jsonrpcx
License: ISC
Keywords: JSON,jsonrpc,rpc
Classifier: License :: OSI Approved :: ISC License (ISCL)
Classifier: Topic :: Internet :: WWW/HTTP :: WSGI
Classifier: Topic :: Internet :: WWW/HTTP :: WSGI :: Application
Classifier: Topic :: Internet :: WWW/HTTP
Classifier: Topic :: Internet :: WWW/HTTP :: HTTP Servers
Classifier: Environment :: Web Environment
Classifier: Intended Audience :: Developers
Classifier: Intended Audience :: System Administrators
Classifier: Operating System :: MacOS :: MacOS X
Classifier: Topic :: Internet
Classifier: Topic :: Home Automation
Classifier: Topic :: Software Development
Classifier: Topic :: Software Development :: Libraries
Classifier: Topic :: Software Development :: Libraries :: Python Modules
Classifier: Topic :: System :: Networking
License-File: LICENCE
Requires-Dist: httpx
Requires-Dist: anyio
Requires-Dist: pytz
Requires-Dist: tzlocal
